evm_architect/__init__.py
evm_architect/architect.py
evm_architect/keymanager.py
evm_architect-1.0.0.dist-info/LICENSE
evm_architect-1.0.0.dist-info/METADATA
evm_architect-1.0.0.dist-info/WHEEL
evm_architect-1.0.0.dist-info/RECORD
