Metadata-Version: 2.1
Name: evm_architect
Version: 1.0.0
Summary: Get the entire architecture of a smart contract system from any address in the architecture
Author: David
Author-email: davidthegardens@gmail.com
Requires-Python: >=3.9,<3.10
Classifier: Programming Language :: Python :: 3
Classifier: Programming Language :: Python :: 3.9
Requires-Dist: mythril (==0.23.25)
Requires-Dist: requests (==2.31.0)
Requires-Dist: web3 (==5.31.1)
Project-URL: Bug Tracker, https://github.com/davidthegardens/EVM_Architect/issues
Project-URL: Homepage, https://github.com/davidthegardens/EVM_Architect
